easykiwi/__init__.py
easykiwi/_singleton.py
easykiwi/cli.py
easykiwi/client.py
easykiwi/core.py
Easykiwi-1.3.dist-info/LICENSE
Easykiwi-1.3.dist-info/METADATA
Easykiwi-1.3.dist-info/WHEEL
Easykiwi-1.3.dist-info/entry_points.txt
Easykiwi-1.3.dist-info/top_level.txt
Easykiwi-1.3.dist-info/RECORD
