Metadata-Version: 2.1
Name: Easykiwi
Version: 1.3
Summary: Easykiwi is a Framework for Queue Messaging Application Development for Python and RabbitMQ.
Home-page: https://github.com/carrasquel/easykiwi
Author: Nelson Carrasquel
Author-email: carrasquel@outlook.com
License: MIT
Platform: UNKNOWN
Classifier: Programming Language :: Python :: 3
Classifier: License :: OSI Approved :: MIT License
Classifier: Operating System :: OS Independent
Requires-Dist: kiwipy
Requires-Dist: aio-pika
Requires-Dist: pyyaml
Requires-Dist: Click (==7.0)
Requires-Dist: python-dotenv (==0.18.0)
